{"timestamp": "2025-07-09T16:31:31.072570", "data": {"realtime_start": "2025-07-09", "realtime_end": "2025-07-09", "observation_start": "2024-07-09", "observation_end": "2025-07-09", "units": "lin", "output_type": 1, "file_type": "json", "order_by": "observation_date", "sort_order": "asc", "count": 12, "offset": 0, "limit": 100000, "observations": [{"realtime_start": "2025-07-09", "realtime_end": "2025-07-09", "date": "2024-07-01", "value": "5.33"}, {"realtime_start": "2025-07-09", "realtime_end": "2025-07-09", "date": "2024-08-01", "value": "5.33"}, {"realtime_start": "2025-07-09", "realtime_end": "2025-07-09", "date": "2024-09-01", "value": "5.13"}, {"realtime_start": "2025-07-09", "realtime_end": "2025-07-09", "date": "2024-10-01", "value": "4.83"}, {"realtime_start": "2025-07-09", "realtime_end": "2025-07-09", "date": "2024-11-01", "value": "4.64"}, {"realtime_start": "2025-07-09", "realtime_end": "2025-07-09", "date": "2024-12-01", "value": "4.48"}, {"realtime_start": "2025-07-09", "realtime_end": "2025-07-09", "date": "2025-01-01", "value": "4.33"}, {"realtime_start": "2025-07-09", "realtime_end": "2025-07-09", "date": "2025-02-01", "value": "4.33"}, {"realtime_start": "2025-07-09", "realtime_end": "2025-07-09", "date": "2025-03-01", "value": "4.33"}, {"realtime_start": "2025-07-09", "realtime_end": "2025-07-09", "date": "2025-04-01", "value": "4.33"}, {"realtime_start": "2025-07-09", "realtime_end": "2025-07-09", "date": "2025-05-01", "value": "4.33"}, {"realtime_start": "2025-07-09", "realtime_end": "2025-07-09", "date": "2025-06-01", "value": "4.33"}], "timestamp": "2025-07-09T16:31:31.072541"}}
