{
  "metadata": {
    "command_name": "cli_enhanced_fundamental_analyst_discover",
    "execution_timestamp": "2025-07-22T14:12:37.000000",
    "framework_phase": "cli_enhanced_discover_7_source",
    "ticker": "AZO",
    "data_collection_methodology": "production_cli_services_unified_access",
    "cli_services_utilized": ["yahoo_finance_cli", "alpha_vantage_cli", "fmp_cli", "fred_economic_cli", "coingecko_cli"],
    "api_keys_configured": "production_keys_from_config/financial_services.yaml"
  },
  "cli_comprehensive_analysis": {
    "metadata": "complete_cli_response_aggregation_from_multi_source_collection",
    "company_overview": "AutoZone, Inc. - specialty automotive aftermarket retailer with 75,600 employees",
    "market_data": "cross_validated_pricing_and_trading_data_3729.7_consistent",
    "analyst_intelligence": "consumer_cyclical_sector_auto_parts_industry_premium_valuation",
    "data_validation": "multi_source_price_validation_with_1.000_confidence",
    "quality_metrics": "institutional_grade_assessment_achieved"
  },
  "market_data": {
    "current_price": 3729.7,
    "market_cap": 62393032704,
    "price_validation": {
      "yahoo_finance_price": 3729.7,
      "alpha_vantage_price": 3729.7,
      "fmp_price": 3729.7,
      "price_consistency": true,
      "confidence_score": 1.0
    },
    "volume": 107565,
    "beta": 0.401,
    "52_week_high": 3916.81,
    "52_week_low": 2894.02,
    "confidence": 0.98
  },
  "financial_metrics": {
    "revenue_ttm": 18490268000,
    "net_income": 2662427000,
    "earnings_per_share": 149.55,
    "pe_ratio": 25.30,
    "profit_margin": 0.1440,
    "return_on_equity": -0.5604,
    "free_cash_flow": 1931420000,
    "revenue_growth": 0.0592,
    "confidence": 0.96
  },
  "company_intelligence": {
    "business_model": {
      "revenue_streams": ["Retail automotive parts sales", "Commercial credit and delivery program", "ALLDATA diagnostic software", "Online sales through autozone.com"],
      "business_segments": {
        "domestic_retail": "6066_stores_united_states",
        "international": "666_stores_mexico_53_stores_brazil",
        "commercial": "b2b_credit_delivery_program",
        "digital": "alldata_diagnostic_software_online_sales"
      },
      "operational_model": "specialty_aftermarket_automotive_retailer_diy_professional_customers",
      "confidence": 0.95
    },
    "financial_statements": {
      "income_statement": {
        "total_revenue_2024": 18490268000,
        "gross_profit_2024": 9817052000,
        "operating_income_2024": 3788708000,
        "net_income_2024": 2662427000,
        "gross_margin": 0.531,
        "operating_margin": 0.205
      },
      "balance_sheet": {
        "total_assets_2024": 17176538000,
        "stockholders_equity_2024": -4749614000,
        "total_debt_2024": 12366969000,
        "working_capital_2024": -1407484000
      },
      "cash_flow": {
        "operating_cash_flow_2024": 3004116000,
        "capital_expenditure_2024": -1072696000,
        "free_cash_flow_2024": 1931420000,
        "common_stock_repurchased_2024": -3140917000
      },
      "total_liquid_assets": 298172000,
      "cash_position_breakdown": {
        "cash_and_equivalents": 298172000,
        "short_term_investments": 0,
        "total_liquid_assets": 298172000
      },
      "investment_portfolio_breakdown": {
        "investments_and_advances": "not_disclosed_separately",
        "cash_and_short_term_investments": 298172000,
        "definition_note": "minimal_liquid_investments_focus_on_operations"
      },
      "confidence": 0.97
    },
    "key_metrics": {
      "business_specific_kpis": ["Store count growth", "Same-store sales growth", "Inventory turnover", "Commercial program growth"],
      "financial_ratios": {
        "current_ratio": 0.84,
        "debt_to_equity": "negative_equity_high_leverage",
        "inventory_turnover": 1.41,
        "asset_turnover": 1.08
      },
      "valuation_multiples": {
        "price_to_earnings": 25.30,
        "price_to_book": "negative_book_value",
        "ev_to_ebitda": 16.74,
        "price_to_sales": 3.37
      },
      "confidence": 0.94
    }
  },
  "cli_market_context": {
    "metadata": "complete_cli_response_aggregation_from_fred_and_coingecko",
    "economic_indicators": {
      "federal_funds_rate": 4.33,
      "unemployment_rate": 4.1,
      "10_year_treasury": 4.38,
      "30_year_mortgage": 6.75
    },
    "cryptocurrency_market": {
      "bitcoin_price": 117254,
      "price_change_24h": -1149.97,
      "market_sentiment": "neutral"
    },
    "market_summary": "neutral_economic_regime_moderate_rates_stable_employment",
    "sector_implications": "consumer_cyclical_sensitivity_to_economic_conditions_moderate"
  },
  "economic_analysis": {
    "interest_rate_environment": "neutral",
    "yield_curve_signal": "normal",
    "policy_implications": ["Moderate monetary policy stance", "Consumer spending stability", "Auto sector cyclical patterns"],
    "sector_sensitivity": "moderate_consumer_discretionary_sensitivity_auto_aftermarket_defensive_characteristics"
  },
  "regulatory_intelligence": {
    "insider_trading_data": "unavailable_no_recent_filings_found",
    "sec_edgar_integration": "framework_ready_10k_10q_available_via_cli",
    "regulatory_analysis": "standard_retail_compliance_automotive_industry_regulations"
  },
  "cli_service_validation": {
    "service_health": {
      "yahoo_finance": "healthy",
      "alpha_vantage": "healthy",
      "fmp": "healthy",
      "fred_economic": "healthy",
      "coingecko": "healthy"
    },
    "health_score": 1.0,
    "services_operational": 5,
    "services_healthy": true
  },
  "cli_data_quality": {
    "overall_data_quality": 0.97,
    "cli_service_health": 1.0,
    "institutional_grade": true,
    "data_sources_via_cli": ["yahoo_finance_cli", "alpha_vantage_cli", "fmp_cli", "fred_economic_cli", "coingecko_cli"],
    "cli_integration_status": "operational"
  },
  "cli_insights": {
    "cli_integration_observations": ["Perfect price consistency across three sources", "Comprehensive financial statement data available", "Real-time economic context integrated", "Production caching optimized performance"],
    "data_quality_insights": ["High confidence in market data validation", "Complete cash flow analysis available", "Enhanced company intelligence via FMP CLI", "Economic indicators fresh and current"],
    "market_context_insights": ["Neutral economic regime supports consumer spending", "Cryptocurrency sentiment neutral", "Interest rates moderate supporting auto sector", "Federal policy stable and predictable"],
    "service_performance_insights": ["All CLI services operational", "Cache optimization reducing API calls", "Multi-source validation enhancing confidence", "Production-grade reliability achieved"]
  },
  "peer_group_data": {
    "peer_companies": [
      {
        "symbol": "ORLY",
        "name": "O'Reilly Automotive",
        "industry": "Specialty Retail - Auto Parts",
        "market_cap_estimate": "similar_scale_primary_competitor"
      },
      {
        "symbol": "AAP",
        "name": "Advance Auto Parts",
        "industry": "Specialty Retail - Auto Parts",
        "market_cap_estimate": "smaller_scale_direct_competitor"
      },
      {
        "symbol": "GPC",
        "name": "Genuine Parts Company",
        "industry": "Auto Parts Distribution",
        "market_cap_estimate": "similar_scale_broader_distribution"
      }
    ],
    "peer_selection_rationale": "Selected based on specialty automotive aftermarket focus, similar business models, and competitive positioning in DIY and professional markets",
    "comparative_metrics": {
      "market_position": "premium_valuation_vs_peers",
      "business_model": "retail_focused_vs_distribution_mix",
      "geographic_focus": "domestic_us_with_mexico_brazil_expansion"
    },
    "confidence": 0.92
  },
  "discovery_insights": {
    "initial_observations": [
      "Strong financial performance with $18.5B revenue and 14.4% profit margins",
      "Negative stockholders equity offset by strong cash generation",
      "Premium valuation at 25.3x P/E suggesting growth expectations",
      "Aggressive share repurchase program with $3.1B in 2024",
      "International expansion in Mexico and Brazil markets"
    ],
    "data_gaps_identified": [
      "Insider trading data unavailable",
      "Detailed segment reporting needs deeper analysis",
      "Peer company financial metrics for comparative analysis",
      "Industry-specific KPIs and benchmarking data"
    ],
    "research_priorities": [
      "Same-store sales growth trends and sustainability",
      "Commercial program expansion and profitability",
      "International market penetration strategy",
      "Inventory management and supply chain efficiency",
      "Capital allocation strategy and dividend policy"
    ],
    "next_phase_readiness": true
  },
  "data_quality_assessment": {
    "source_reliability_scores": {
      "yahoo_finance_cli": 0.98,
      "alpha_vantage_cli": 0.97,
      "fmp_cli": 0.98,
      "fred_economic_cli": 0.99,
      "coingecko_cli": 0.96
    },
    "data_completeness": 0.96,
    "data_freshness": {
      "market_data": "real_time_current",
      "financial_statements": "latest_available_2024_annual",
      "economic_indicators": "current_june_2025",
      "company_profile": "current_comprehensive"
    },
    "quality_flags": [
      "perfect_price_consistency_across_sources",
      "comprehensive_financial_statement_data_including_cash_flow",
      "enhanced_financial_metrics_with_calculated_ratios",
      "real_time_economic_context_integration",
      "institutional_grade_confidence_achieved"
    ]
  }
}
