{
  "metadata": {
    "command_name": "sector_analyst_analyze",
    "execution_timestamp": "2025-07-12T13:20:00.000000",
    "framework_phase": "analyze",
    "sector": "consumer_staples",
    "analysis_methodology": "template_gap_analysis",
    "discovery_file_reference": "consumer_staples_20250712_discovery.json",
    "confidence_threshold": 0.9
  },
  "business_cycle_positioning": {
    "current_phase": "late_cycle",
    "recession_probability": 0.35,
    "historical_performance_by_phase": {
      "early_cycle": {
        "relative_performance": -2.5,
        "typical_duration_quarters": 6,
        "sector_characteristics": "underperforms_growth_sectors_preferred"
      },
      "mid_cycle": {
        "relative_performance": -1.8,
        "typical_duration_quarters": 12,
        "sector_characteristics": "modest_underperformance_stable_growth"
      },
      "late_cycle": {
        "relative_performance": 1.2,
        "typical_duration_quarters": 8,
        "sector_characteristics": "defensive_positioning_becomes_attractive"
      },
      "recession": {
        "relative_performance": 4.8,
        "typical_duration_quarters": 4,
        "sector_characteristics": "significant_outperformance_flight_to_quality"
      }
    },
    "interest_rate_sensitivity": {
      "duration_analysis": 3.2,
      "leverage_impact": "low_moderate_sector_debt_levels",
      "rate_coefficients": {
        "fed_funds_correlation": -0.15,
        "10yr_treasury_correlation": -0.22,
        "yield_curve_sensitivity": 0.08
      },
      "rate_transmission_mechanism": "consumer_spending_patterns_and_dividend_yields"
    },
    "inflation_hedge_assessment": {
      "pricing_power": "moderate_to_strong_brand_pricing_power",
      "real_return_protection": 0.68,
      "cost_structure_flexibility": {
        "input_cost_pass_through": 0.75,
        "operational_leverage": "low_fixed_cost_base",
        "margin_protection": "strong_during_moderate_inflation"
      },
      "historical_inflation_correlation": 0.42
    },
    "gdp_growth_correlation": {
      "gdp_elasticity": 0.35,
      "historical_correlation": 0.28,
      "expansion_performance": {
        "avg_relative_return": -3.2,
        "volatility_during_expansion": 12.8,
        "correlation_strength": "weak_positive"
      },
      "contraction_performance": {
        "avg_relative_return": 6.1,
        "volatility_during_contraction": 8.4,
        "defensive_characteristics": "strong_recession_protection"
      },
      "leading_lagging_relationship": "lagging_indicator_with_defensive_timing"
    },
    "confidence": 0.92
  },
  "liquidity_cycle_positioning": {
    "fed_policy_stance": "restrictive",
    "credit_market_conditions": {
      "corporate_bond_issuance": "adequate_access_for_quality_names",
      "credit_spreads": {
        "sector_vs_treasury": 125,
        "trend": "stable_to_tightening",
        "relative_to_market": "tighter_than_average"
      },
      "refinancing_risk": "low_well_laddered_maturities",
      "banking_standards": "tightening_but_manageable_for_sector"
    },
    "money_supply_impact": {
      "m2_growth_sensitivity": 0.18,
      "velocity_implications": "defensive_demand_less_velocity_sensitive",
      "asset_price_inflation": {
        "valuation_multiple_impact": "moderate_pe_compression_risk",
        "real_asset_correlation": 0.22
      }
    },
    "liquidity_preferences": {
      "sector_allocation_flows": "defensive_allocation_increasing",
      "risk_appetite_correlation": -0.34,
      "flight_to_quality_impact": "strong_beneficiary_during_stress"
    },
    "employment_sensitivity": {
      "payroll_correlation": 0.15,
      "labor_participation_impact": "minimal_necessary_goods_consumption",
      "initial_claims_signaling": {
        "correlation_coefficient": -0.12,
        "early_warning_threshold": 450000,
        "sector_response_lag": "2_3_quarters"
      },
      "employment_cycle_positioning": "defensive_across_all_employment_phases",
      "consumer_spending_linkage": {
        "discretionary_vs_staples": "inverse_relationship_during_stress",
        "employment_elasticity": 0.08,
        "income_effect_strength": "low_necessity_goods"
      }
    },
    "confidence": 0.88
  },
  "industry_dynamics_scorecard": {
    "profitability_score": {
      "grade": "B+",
      "trend": "stable",
      "key_metrics": {
        "sector_avg_net_margin": 8.2,
        "margin_stability_score": 4.1,
        "roe_quality": "consistent_mid_teens"
      },
      "supporting_evidence": {
        "margin_resilience": "stable_margins_across_cycles",
        "pricing_power": "brand_strength_supports_pricing",
        "cost_management": "efficient_supply_chain_optimization"
      }
    },
    "balance_sheet_score": {
      "grade": "A-",
      "trend": "stable",
      "debt_trends": {
        "avg_debt_to_equity": 0.42,
        "interest_coverage": 12.8,
        "leverage_trend": "stable_to_improving"
      },
      "liquidity_adequacy": {
        "current_ratio": 1.35,
        "quick_ratio": 0.98,
        "cash_position": "adequate_working_capital"
      }
    },
    "competitive_moat_score": {
      "score": 7.5,
      "moat_strength": "strong_brand_recognition_and_distribution",
      "sustainability": {
        "brand_durability": "decades_long_consumer_loyalty",
        "distribution_networks": "entrenched_retail_relationships",
        "economies_of_scale": "significant_manufacturing_advantages"
      },
      "evidence": {
        "market_share_stability": "consistent_leadership_positions",
        "pricing_power_demonstration": "successful_price_increases",
        "private_label_resistance": "premium_brand_positioning"
      }
    },
    "regulatory_environment_rating": {
      "rating": "neutral",
      "policy_timeline": {
        "near_term_changes": "incremental_labeling_requirements",
        "medium_term_outlook": "sustainability_packaging_mandates",
        "long_term_trends": "health_nutrition_focus_increasing"
      },
      "compliance_costs": {
        "current_burden": "manageable_2_3_percent_of_revenue",
        "incremental_costs": "modest_increases_expected",
        "competitive_impact": "uniform_across_industry"
      },
      "industry_influence": "strong_lobbying_presence_moderate_capture"
    },
    "confidence": 0.91
  },
  "multi_method_valuation": {
    "dcf_analysis": {
      "fair_value": 84.50,
      "wacc": 7.8,
      "growth_assumptions": {
        "near_term_growth": 3.2,
        "terminal_growth": 2.5,
        "fcf_conversion": 0.88
      },
      "sensitivity_analysis": {
        "wacc_plus_50bp": 81.20,
        "wacc_minus_50bp": 88.10,
        "growth_plus_50bp": 87.80,
        "growth_minus_50bp": 81.40
      },
      "weight": 40
    },
    "relative_comps": {
      "fair_value": 82.75,
      "peer_multiples": {
        "forward_pe": 22.5,
        "ev_ebitda": 14.2,
        "price_to_book": 3.1,
        "dividend_yield": 2.8
      },
      "premium_discount": {
        "vs_sector_median": -2.1,
        "justification": "defensive_characteristics_warrant_modest_premium",
        "quality_adjustment": 1.8
      },
      "multiple_trends": {
        "pe_compression_risk": "moderate_in_restrictive_environment",
        "historical_range": "20x_to_26x_forward_pe",
        "current_positioning": "middle_of_historical_range"
      },
      "weight": 35
    },
    "technical_analysis": {
      "fair_value": 83.25,
      "support_resistance": {
        "key_support": 78.50,
        "key_resistance": 85.00,
        "breakout_target": 88.50
      },
      "momentum_indicators": {
        "rsi": 52,
        "macd_signal": "neutral_to_positive",
        "trend_strength": "moderate_uptrend"
      },
      "volume_profile": {
        "accumulation_zones": "80_00_to_82_00",
        "distribution_concerns": "minimal_at_current_levels",
        "institutional_flow": "steady_defensive_allocation"
      },
      "weight": 25
    },
    "blended_valuation": {
      "weighted_fair_value": 83.65,
      "confidence_intervals": {
        "bull_case": 87.20,
        "base_case": 83.65,
        "bear_case": 79.80
      },
      "scenario_weighting": {
        "bull_probability": 0.25,
        "base_probability": 0.50,
        "bear_probability": 0.25
      }
    },
    "etf_price_vs_fair_value_analysis": {
      "current_etf_price": 80.81,
      "fair_value_range": {
        "low_end": 79.80,
        "mid_point": 83.65,
        "high_end": 87.20
      },
      "price_gap_analysis": {
        "current_vs_fair_value": -3.4,
        "percentage_undervalued": 3.5,
        "position_in_range": "bottom_quartile"
      },
      "recommendation_validation": {
        "current_recommendation": "BUY",
        "logic": "trading_below_fair_value_with_defensive_characteristics",
        "price_target": 83.65,
        "upside_potential": 3.5
      },
      "price_positioning": "below_fair_value_range",
      "etf_price_consistency": 1.0
    },
    "confidence": 0.89
  },
  "quantified_risk_assessment": {
    "risk_matrix": {
      "economic_recession": {
        "probability": 0.35,
        "impact": 2,
        "risk_score": 0.70,
        "rationale": "defensive_characteristics_limit_recession_impact"
      },
      "interest_rate_shock": {
        "probability": 0.25,
        "impact": 3,
        "risk_score": 0.75,
        "rationale": "dividend_yields_and_consumer_behavior_sensitivity"
      },
      "dollar_strength": {
        "probability": 0.40,
        "impact": 2,
        "risk_score": 0.80,
        "rationale": "mixed_exposure_multinational_vs_domestic_focus"
      },
      "regulatory_changes": {
        "probability": 0.60,
        "impact": 2,
        "risk_score": 1.20,
        "rationale": "ongoing_health_sustainability_regulatory_trends"
      },
      "market_volatility": {
        "probability": 0.70,
        "impact": 1,
        "risk_score": 0.70,
        "rationale": "defensive_sector_benefits_from_volatility"
      }
    },
    "stress_testing": {
      "bear_market_scenario": {
        "probability": 25,
        "sector_impact": -12.0,
        "recovery_timeline": 6,
        "relative_performance": 8.0
      },
      "recession_scenario": {
        "probability": 35,
        "sector_impact": -8.5,
        "recovery_phases": "faster_recovery_than_cyclicals",
        "defensive_outperformance": 12.0
      },
      "policy_shock_scenario": {
        "probability": 20,
        "regulatory_impact": "moderate_compliance_cost_increases",
        "implementation_timeline": "2_3_year_phase_in"
      }
    },
    "sensitivity_analysis": {
      "key_variables": [
        "consumer_spending_growth",
        "input_cost_inflation",
        "interest_rates",
        "private_label_penetration"
      ],
      "elasticity_calculations": {
        "spending_growth_1pct": 0.8,
        "input_cost_inflation_1pct": -0.4,
        "interest_rate_100bp": -1.2,
        "private_label_1pct": -0.6
      },
      "break_even_analysis": {
        "margin_compression_threshold": 150,
        "volume_decline_threshold": -8.0,
        "pricing_power_minimum": 2.5
      },
      "tornado_diagram": [
        "consumer_spending_growth",
        "interest_rates",
        "private_label_penetration",
        "input_cost_inflation"
      ]
    },
    "aggregate_risk_score": 3.45,
    "confidence": 0.86
  },
  "enhanced_economic_sensitivity": {
    "fed_funds_correlation": -0.15,
    "dxy_impact": {
      "correlation_coefficient": -0.08,
      "multinational_exposure": "mixed_impact_across_companies",
      "domestic_focus_benefit": "local_brands_less_currency_sensitive"
    },
    "yield_curve_analysis": {
      "basis_point_impact_per_curve_change": -0.12,
      "inversion_impact": "negative_for_consumer_discretionary_positive_for_staples",
      "steepening_sensitivity": "modest_positive_impact"
    },
    "crypto_correlation": {
      "bitcoin_correlation_coefficient": -0.18,
      "risk_appetite_inverse": "defensive_characteristics_inverse_to_speculation",
      "institutional_flow_impact": "crypto_outflows_benefit_defensive_sectors"
    },
    "economic_indicators": {
      "unemployment_sensitivity": -0.22,
      "inflation_sensitivity": 0.31,
      "gdp_correlation": 0.28
    },
    "confidence": 0.84
  },
  "macroeconomic_risk_scoring": {
    "gdp_based_risk_assessment": {
      "gdp_deceleration_probability": 0.42,
      "recession_vulnerability": 0.25,
      "gdp_elasticity_impact": {
        "1pct_gdp_decline": -0.35,
        "recession_outperformance": 6.1,
        "recovery_lag": "1_2_quarters"
      },
      "early_warning_signals": [
        "consumer_confidence_below_90",
        "gdp_growth_below_1_percent",
        "yield_curve_inverted_6_months"
      ]
    },
    "employment_based_risk_assessment": {
      "payroll_decline_probability": 0.28,
      "labor_market_impact": {
        "unemployment_rise_impact": "minimal_necessary_goods_demand",
        "job_loss_consumer_response": "trade_down_within_staples_category",
        "employment_elasticity": 0.08
      },
      "claims_spike_scenarios": {
        "450k_threshold_probability": 0.22,
        "sector_stress_correlation": "low_defensive_characteristics",
        "response_timeline": "2_3_quarter_lag"
      },
      "employment_cycle_risk": "low_across_all_employment_phases"
    },
    "combined_macroeconomic_risk": {
      "composite_risk_index": 0.31,
      "cross_correlation_analysis": {
        "gdp_employment_interaction": "reinforcing_defensive_characteristics",
        "shock_amplification": "minimal_in_consumer_staples",
        "risk_mitigation": "diversified_necessity_goods_portfolio"
      },
      "recession_probability": 0.35,
      "stress_test_outcomes": {
        "mild_recession_scenario": -8.5,
        "severe_recession_scenario": -15.2,
        "relative_outperformance": 8.0
      }
    },
    "early_warning_system": {
      "leading_indicators": [
        "consumer_confidence_index",
        "initial_jobless_claims_4_week_average",
        "yield_curve_10y_2y_spread",
        "real_gdp_growth_rate"
      ],
      "threshold_breach_probability": {
        "consumer_confidence_below_90": 0.35,
        "claims_above_450k": 0.22,
        "yield_curve_inverted_6mo": 0.60,
        "gdp_below_1pct": 0.38
      },
      "monitoring_kpis": [
        "same_store_sales_growth",
        "private_label_penetration_rate",
        "margin_compression_indicators",
        "inventory_turnover_deterioration"
      ],
      "risk_escalation_triggers": [
        "consumer_confidence_below_80",
        "unemployment_above_5_percent",
        "yield_curve_inverted_12_months",
        "consecutive_negative_gdp_quarters"
      ]
    },
    "confidence": 0.88
  },
  "investment_recommendation_gap_analysis": {
    "portfolio_allocation_context": {
      "sector_weighting_recommendations": {
        "current_market_weight": 6.8,
        "recommended_allocation": 8.5,
        "overweight_rationale": "defensive_positioning_late_cycle_environment",
        "allocation_range": {
          "minimum": 6.0,
          "target": 8.5,
          "maximum": 12.0
        }
      },
      "cross_sector_optimization": {
        "correlation_based_adjustments": "low_correlation_with_technology_financials",
        "diversification_benefit": "strong_portfolio_risk_reduction",
        "rebalancing_frequency": "quarterly_with_economic_cycle_monitoring"
      },
      "economic_cycle_rotation": {
        "late_cycle_allocation": "increase_to_overweight_position",
        "recession_allocation": "maintain_overweight_defensive_positioning",
        "early_recovery_allocation": "reduce_to_market_weight",
        "rotation_probability": 0.75
      },
      "risk_adjusted_positioning": {
        "sharpe_ratio_improvement": 0.15,
        "portfolio_volatility_reduction": -1.8,
        "downside_protection": "significant_during_market_stress"
      },
      "confidence": 0.91
    },
    "economic_cycle_investment_positioning": {
      "rotation_probability_analysis": {
        "out_of_staples_probability": 0.25,
        "into_staples_probability": 0.65,
        "timing_considerations": "late_cycle_defensive_rotation_underway"
      },
      "economic_timing_considerations": {
        "fed_policy_impact": "restrictive_policy_supports_defensive_allocation",
        "fiscal_policy_implications": "neutral_to_positive_for_staples_consumption",
        "international_factors": "global_slowdown_supports_defensive_positioning"
      },
      "business_cycle_allocation": {
        "current_phase_optimal": "late_cycle_overweight_recommended",
        "next_phase_positioning": "maintain_defensive_allocation",
        "tactical_timing": "gradual_accumulation_on_weakness"
      },
      "policy_impact_assessment": {
        "monetary_policy": "restrictive_rates_support_dividend_appeal",
        "regulatory_policy": "manageable_incremental_compliance_costs",
        "trade_policy": "minimal_impact_domestic_focus"
      },
      "confidence": 0.89
    },
    "risk_adjusted_investment_metrics": {
      "sector_sharpe_calculation": {
        "current_sharpe_ratio": 0.74,
        "risk_adjusted_return": 6.98,
        "volatility_adjusted": 9.41,
        "economic_context_adjustment": 0.08
      },
      "downside_risk_assessment": {
        "maximum_drawdown_estimate": -18.5,
        "value_at_risk_95": -12.2,
        "stress_scenario_protection": "significant_defensive_characteristics"
      },
      "volatility_adjusted_returns": {
        "risk_parity_weighting": 12.5,
        "minimum_variance_contribution": "strong_portfolio_stabilizer",
        "economic_cycle_volatility": "lower_volatility_across_all_phases"
      },
      "stress_testing_scenarios": {
        "2008_financial_crisis": -15.2,
        "2020_covid_pandemic": -8.7,
        "1970s_stagflation": 12.4
      },
      "confidence": 0.87
    },
    "investment_conclusion_confidence": {
      "thesis_confidence_methodology": {
        "fundamental_analysis_weight": 0.4,
        "economic_cycle_weight": 0.3,
        "technical_analysis_weight": 0.2,
        "sentiment_analysis_weight": 0.1
      },
      "economic_factor_weighting": {
        "gdp_correlation_confidence": 0.85,
        "employment_correlation_confidence": 0.88,
        "inflation_hedge_confidence": 0.82,
        "interest_rate_sensitivity_confidence": 0.84
      },
      "allocation_guidance_confidence": {
        "portfolio_optimization_reliability": 0.89,
        "risk_reduction_confidence": 0.92,
        "return_enhancement_confidence": 0.78
      },
      "relative_positioning_confidence": {
        "vs_growth_sectors": 0.94,
        "vs_defensive_sectors": 0.86,
        "vs_cyclical_sectors": 0.91
      },
      "confidence": 0.88
    },
    "sector_investment_characteristics": {
      "growth_defensive_classification": "pure_defensive_with_modest_growth",
      "interest_rate_sensitivity": {
        "duration_risk": "low_3_2_years",
        "rate_cycle_positioning": "benefits_from_restrictive_to_neutral_transition",
        "dividend_yield_support": "attractive_yields_in_higher_rate_environment"
      },
      "economic_sensitivity_profile": {
        "gdp_elasticity": 0.35,
        "employment_elasticity": 0.08,
        "inflation_correlation": 0.31,
        "recession_beta": -0.25
      },
      "investment_risk_opportunities": {
        "primary_risks": [
          "private_label_competition",
          "input_cost_inflation",
          "consumer_trade_down"
        ],
        "primary_opportunities": [
          "defensive_portfolio_allocation",
          "dividend_income_stability",
          "late_cycle_outperformance"
        ]
      },
      "confidence": 0.90
    },
    "etf_price_recommendation_framework": {
      "etf_price_validation": {
        "current_price_accuracy": 1.0,
        "cross_source_consistency": 1.0,
        "real_time_validation": "confirmed_80_81"
      },
      "fair_value_positioning": {
        "current_position": "below_fair_value",
        "undervaluation_percentage": 3.5,
        "value_opportunity": "modest_upside_to_fair_value"
      },
      "recommendation_logic": {
        "buy_threshold": "below_82_00",
        "hold_range": "82_00_to_85_00",
        "sell_threshold": "above_87_00",
        "current_recommendation": "BUY",
        "price_target": 83.65
      },
      "price_gap_assessment": {
        "fair_value_gap": -3.4,
        "technical_gap": -2.4,
        "fundamental_gap": -2.8,
        "weighted_gap": -2.9
      },
      "etf_price_risk_assessment": {
        "downside_risk": "limited_below_78_50_support",
        "upside_opportunity": "3_5_percent_to_fair_value",
        "risk_reward_ratio": "favorable_1_85_to_1"
      },
      "confidence": 0.92
    }
  },
  "analysis_quality_metrics": {
    "gap_coverage": 0.94,
    "confidence_propagation": {
      "discovery_confidence_inherited": 0.95,
      "analytical_enhancement": 0.89,
      "combined_confidence": 0.92
    },
    "analytical_rigor": {
      "methodology_quality_score": 0.91,
      "quantitative_support": 0.88,
      "evidence_strength": 0.90
    },
    "evidence_strength": {
      "financial_data_quality": 0.95,
      "economic_correlation_strength": 0.84,
      "historical_pattern_reliability": 0.87,
      "forward_looking_assumptions": 0.82
    }
  }
}
