{
  "metadata": {
    "command_name": "fundamental_analyst_analyze",
    "execution_timestamp": "2025-07-03T16:30:00Z",
    "framework_phase": "analyze",
    "ticker": "EXR",
    "analysis_methodology": "systematic_evaluation_framework"
  },
  "financial_health_analysis": {
    "profitability_assessment": {
      "gross_margin_analysis": {
        "revenue_quality": "Premium rental income from 4,099 owned properties with diversified revenue streams",
        "margin_stability": "Operating margin of 43.02% demonstrates strong operational efficiency",
        "margin_drivers": [
          "Premium market positioning in self-storage sector",
          "Economies of scale from largest operator status",
          "Revenue diversification through management fees and bridge loans"
        ],
        "peer_comparison": "Operating margin exceeds industry average of ~38-40%",
        "trend_analysis": "Margins under pressure from market softness but supported by scale advantages"
      },
      "operating_leverage": {
        "fixed_cost_base": "High fixed costs from property ownership create significant operating leverage",
        "revenue_sensitivity": "Revenue growth flows directly to operating income due to operational structure",
        "scalability": "Demonstrated ability to scale operations efficiently through Life Storage acquisition",
        "leverage_coefficient": 2.3
      },
      "ebitda_quality": {
        "ebitda_amount": 2311807000,
        "ebitda_margin": 0.7102,
        "quality_adjustments": {
          "one_time_items": "Minimal non-recurring adjustments",
          "non_cash_charges": "Depreciation represents majority of EBITDA add-backs",
          "working_capital_impact": "Limited working capital requirements in REIT structure"
        },
        "sustainability": "High-quality EBITDA supported by recurring rental income"
      },
      "cash_conversion": {
        "operating_cash_flow": 1887430000,
        "free_cash_flow": 1866916000,
        "conversion_rate": 0.989,
        "capex_intensity": 0.006,
        "cash_conversion_quality": "Excellent conversion with minimal capex requirements"
      },
      "grade": "A-",
      "trend": "stable",
      "confidence": 0.88
    },
    "balance_sheet_strength": {
      "liquidity_analysis": {
        "current_ratio": 0.931,
        "quick_ratio": 0.931,
        "cash_position": 138222000,
        "total_liquid_assets": 438222000,
        "liquidity_adequacy": "Adequate liquidity for operations, though current ratio below 1.0 requires monitoring",
        "credit_facilities": "Access to credit facilities and capital markets for funding needs"
      },
      "leverage_metrics": {
        "debt_to_equity": 0.934,
        "total_debt": 13027861000,
        "interest_coverage": 6.85,
        "net_debt_to_ebitda": 5.57,
        "debt_structure": "Primarily fixed-rate debt with laddered maturities",
        "covenant_compliance": "Maintains comfortable covenant cushions"
      },
      "working_capital": {
        "working_capital_amount": -145000000,
        "working_capital_efficiency": "Negative working capital typical for REIT structure",
        "receivables_management": "Limited receivables due to monthly rental model",
        "payables_optimization": "Efficient payables management"
      },
      "off_balance_sheet": {
        "commitments": "Development commitments and lease obligations",
        "contingencies": "Standard litigation and environmental contingencies",
        "material_exposures": "Bridge loan portfolio creates credit exposure"
      },
      "grade": "B+",
      "trend": "stable",
      "confidence": 0.85
    },
    "cash_flow_analysis": {
      "operating_cash_flow": {
        "amount": 1887430000,
        "quality": "High-quality recurring cash flows from rental operations",
        "predictability": "Highly predictable due to lease structure and market leadership",
        "growth_trajectory": "Stable with potential for recovery as market conditions improve"
      },
      "free_cash_flow": {
        "amount": 1866916000,
        "margin": 0.573,
        "after_dividend_fcf": 491913000,
        "fcf_conversion": "Strong conversion from operating cash flow",
        "sustainability": "Sustainable given low capex requirements"
      },
      "capital_allocation": {
        "dividend_policy": "Consistent dividend payments with 4.4% yield",
        "dividend_coverage": 1.36,
        "growth_investments": "Selective acquisition strategy and development programs",
        "shareholder_returns": "Strong total returns through dividends and capital appreciation",
        "allocation_quality": "Balanced approach to growth and income"
      },
      "sustainability": {
        "cash_flow_stability": "Highly stable recurring revenue model",
        "cyclical_sensitivity": "Moderate sensitivity to economic cycles",
        "competitive_moats": "Market leadership provides cash flow protection"
      },
      "grade": "A",
      "trend": "stable",
      "confidence": 0.90
    },
    "capital_efficiency": {
      "roic_analysis": {
        "return_on_invested_capital": 0.0485,
        "wacc_estimate": 0.065,
        "roic_wacc_spread": -0.0165,
        "trend_analysis": "ROIC below WACC due to recent acquisition integration",
        "improvement_trajectory": "Expected improvement as Life Storage synergies realize"
      },
      "asset_utilization": {
        "asset_turnover": 0.113,
        "property_utilization": "~90% occupancy rate across portfolio",
        "revenue_per_sqft": "Premium pricing in most markets",
        "asset_quality": "High-quality properties in prime locations"
      },
      "management_execution": {
        "strategic_initiatives": "Successful Life Storage acquisition and integration",
        "operational_improvements": "Technology investments improving efficiency",
        "capital_deployment": "Disciplined approach to acquisitions and development"
      },
      "reinvestment_quality": {
        "growth_capex": "Selective development and property improvements",
        "maintenance_capex": "Minimal requirements due to asset nature",
        "acquisition_returns": "Strong track record of accretive acquisitions"
      },
      "grade": "B",
      "trend": "improving",
      "confidence": 0.82
    }
  },
  "competitive_position_assessment": {
    "market_position": {
      "market_share_trends": {
        "current_share": 0.141,
        "market_position": "Largest self-storage operator in United States",
        "share_trajectory": "Gaining share through strategic acquisitions",
        "competitive_dynamics": "Consolidating fragmented industry"
      },
      "pricing_power": {
        "premium_positioning": "Commands premium pricing in most markets",
        "price_elasticity": "Moderate elasticity due to convenience factors",
        "pricing_strategy": "Dynamic pricing implementation across portfolio"
      },
      "customer_analysis": {
        "customer_concentration": "Highly diversified customer base",
        "retention_rates": "Strong customer retention due to switching costs",
        "acquisition_costs": "Moderate acquisition costs through digital marketing"
      },
      "competitive_dynamics": {
        "market_structure": "Consolidating industry with few large players",
        "competitive_intensity": "Moderate competition in most markets",
        "differentiation_factors": "Scale, technology, and operational excellence"
      },
      "confidence": 0.87
    },
    "moat_assessment": {
      "identified_moats": [
        {
          "moat_type": "Scale advantages",
          "strength": "Strong",
          "description": "Largest operator with 4,099 properties enables operational efficiencies",
          "durability": "High durability - scale advantages compound over time"
        },
        {
          "moat_type": "Switching costs",
          "strength": "Moderate",
          "description": "Customer switching costs due to convenience and location factors",
          "durability": "Moderate durability - location-dependent"
        },
        {
          "moat_type": "Network effects",
          "strength": "Weak",
          "description": "Limited network effects in self-storage business model",
          "durability": "Low durability - primarily location-based business"
        },
        {
          "moat_type": "Brand recognition",
          "strength": "Moderate",
          "description": "Extended Stay America brand recognition in self-storage",
          "durability": "Moderate durability - brand matters for customer acquisition"
        }
      ],
      "moat_strength_ratings": {
        "overall_moat_strength": "Moderate-to-Strong",
        "primary_moat": "Scale advantages and operational efficiency",
        "secondary_moat": "Location portfolio and switching costs"
      },
      "durability_analysis": {
        "5_year_outlook": "Strong - scale advantages likely to persist",
        "10_year_outlook": "Moderate - potential disruption from technology",
        "sustainability_factors": "Location advantages, operational scale, customer inertia"
      },
      "evidence_backing": {
        "market_share_data": "14.1% market share significantly ahead of competitors",
        "operational_metrics": "43.02% operating margin exceeds industry average",
        "customer_metrics": "Strong retention and pricing power evidence"
      },
      "confidence": 0.83
    },
    "industry_dynamics": {
      "market_growth": {
        "total_addressable_market": "~$32 billion US self-storage market",
        "growth_rate": "Historical 3-5% annual growth, currently pressured",
        "growth_drivers": [
          "Urbanization and smaller living spaces",
          "Life transitions and mobility",
          "Business storage needs"
        ],
        "market_maturity": "Mature market with cyclical characteristics"
      },
      "competitive_intensity": {
        "rivalry_level": "Moderate - consolidated industry with few major players",
        "barriers_to_entry": "High barriers due to real estate requirements and capital needs",
        "supplier_power": "Low - commoditized construction and materials",
        "buyer_power": "Low - individual consumers with limited alternatives"
      },
      "disruption_risk": {
        "technology_disruption": "Low risk - physical storage requirements unchanged",
        "business_model_disruption": "Moderate risk from alternative storage solutions",
        "regulatory_disruption": "Low risk - limited regulatory oversight"
      },
      "regulatory_environment": {
        "regulatory_complexity": "Moderate - primarily local zoning and building codes",
        "regulatory_trends": "Stable regulatory environment",
        "compliance_costs": "Manageable compliance requirements"
      },
      "confidence": 0.85
    }
  },
  "growth_analysis": {
    "historical_decomposition": {
      "growth_drivers": {
        "organic_growth": "Challenged by market softness and oversupply",
        "acquisition_growth": "Significant growth from Life Storage acquisition",
        "pricing_contribution": "Limited pricing power in current environment",
        "volume_contribution": "Occupancy rates under pressure"
      },
      "growth_quality": {
        "revenue_growth_rate": 0.272,
        "growth_sustainability": "Recent growth driven by acquisition, organic growth challenged",
        "profitability_growth": "Margins maintained despite revenue headwinds"
      },
      "sustainability": {
        "competitive_position": "Market leadership supports long-term growth",
        "market_dynamics": "Cyclical downturn expected to recover",
        "execution_capability": "Strong operational execution and integration capabilities"
      },
      "confidence": 0.80
    },
    "future_catalysts": {
      "identified_catalysts": [
        {
          "catalyst": "Self-storage market recovery",
          "probability": 0.75,
          "impact": "High - would drive occupancy and pricing improvement",
          "timeline": "12-24 months",
          "dependencies": "Economic stability and reduced new supply"
        },
        {
          "catalyst": "Life Storage integration synergies",
          "probability": 0.85,
          "impact": "Medium - cost savings and operational improvements",
          "timeline": "6-18 months",
          "dependencies": "Successful integration execution"
        },
        {
          "catalyst": "Technology platform monetization",
          "probability": 0.60,
          "impact": "Medium - improved efficiency and customer experience",
          "timeline": "12-36 months",
          "dependencies": "Technology development and adoption"
        }
      ],
      "probability_estimates": {
        "base_case_scenario": 0.60,
        "upside_scenario": 0.25,
        "downside_scenario": 0.15
      },
      "impact_quantification": {
        "market_recovery_impact": "10-15% revenue upside potential",
        "synergy_impact": "$50-75M annual cost savings",
        "technology_impact": "3-5% operational efficiency improvement"
      },
      "timeline_analysis": {
        "near_term_catalysts": "Integration synergies and operational improvements",
        "medium_term_catalysts": "Market recovery and technology benefits",
        "long_term_catalysts": "Market share gains and expansion opportunities"
      },
      "confidence": 0.78
    },
    "management_assessment": {
      "track_record": {
        "strategic_execution": "Strong track record of successful acquisitions",
        "operational_performance": "Consistent operational excellence and efficiency",
        "financial_management": "Disciplined capital allocation and balance sheet management"
      },
      "capital_allocation": {
        "dividend_policy": "Consistent dividend payments with sustainable payout ratio",
        "acquisition_strategy": "Selective acquisition approach with focus on accretive deals",
        "development_projects": "Disciplined development with strong returns"
      },
      "strategic_execution": {
        "life_storage_integration": "Successful integration of largest acquisition",
        "technology_initiatives": "Investment in digital platforms and automation",
        "market_positioning": "Strengthening market leadership position"
      },
      "credibility_score": 0.85,
      "confidence": 0.82
    }
  },
  "risk_assessment": {
    "risk_matrix": {
      "operational_risks": [
        {
          "risk": "Occupancy rate decline",
          "probability": 0.6,
          "impact": 4,
          "mitigation": "Pricing flexibility and cost management",
          "evidence": "Current market softness and oversupply"
        },
        {
          "risk": "Technology disruption",
          "probability": 0.3,
          "impact": 3,
          "mitigation": "Investment in digital platforms",
          "evidence": "Limited disruption risk in physical storage"
        }
      ],
      "financial_risks": [
        {
          "risk": "Interest rate sensitivity",
          "probability": 0.7,
          "impact": 3,
          "mitigation": "Fixed-rate debt and laddered maturities",
          "evidence": "REIT structure creates interest rate sensitivity"
        },
        {
          "risk": "Refinancing risk",
          "probability": 0.4,
          "impact": 3,
          "mitigation": "Strong credit profile and market access",
          "evidence": "Debt maturity schedule and covenant compliance"
        }
      ],
      "competitive_risks": [
        {
          "risk": "Increased competition",
          "probability": 0.5,
          "impact": 3,
          "mitigation": "Scale advantages and operational efficiency",
          "evidence": "Market consolidation trends"
        },
        {
          "risk": "Pricing pressure",
          "probability": 0.7,
          "impact": 4,
          "mitigation": "Cost management and operational leverage",
          "evidence": "Current market conditions showing pricing pressure"
        }
      ],
      "regulatory_risks": [
        {
          "risk": "Zoning restrictions",
          "probability": 0.3,
          "impact": 2,
          "mitigation": "Diversified geographic footprint",
          "evidence": "Limited regulatory oversight historically"
        }
      ],
      "macro_risks": [
        {
          "risk": "Economic recession",
          "probability": 0.4,
          "impact": 4,
          "mitigation": "Defensive business model and strong balance sheet",
          "evidence": "Self-storage typically resilient in downturns"
        },
        {
          "risk": "Real estate cycle downturn",
          "probability": 0.6,
          "impact": 4,
          "mitigation": "Market leadership and operational efficiency",
          "evidence": "Current challenging real estate environment"
        }
      ]
    },
    "quantified_assessment": {
      "aggregate_risk_score": 3.2,
      "risk_probability_distribution": {
        "low_risk": 0.30,
        "medium_risk": 0.50,
        "high_risk": 0.20
      },
      "detailed_probability_impact_matrix": {
        "operational_risks_score": 3.4,
        "financial_risks_score": 3.1,
        "competitive_risks_score": 3.5,
        "regulatory_risks_score": 1.6,
        "macro_risks_score": 3.2
      },
      "stress_testing_scenarios": {
        "severe_recession": {
          "occupancy_impact": "-15%",
          "pricing_impact": "-10%",
          "revenue_impact": "-22%",
          "probability": 0.15
        },
        "interest_rate_shock": {
          "refinancing_cost": "+200bps",
          "valuation_impact": "-15%",
          "probability": 0.25
        }
      },
      "sensitivity_analysis": {
        "occupancy_rate_sensitivity": "±1% occupancy = ±$32M revenue",
        "pricing_sensitivity": "±1% pricing = ±$28M revenue",
        "interest_rate_sensitivity": "±100bps = ±$130M annual interest expense"
      },
      "mitigation_strategies": {
        "operational": "Dynamic pricing and cost management",
        "financial": "Debt management and liquidity maintenance",
        "competitive": "Scale advantages and operational excellence"
      },
      "monitoring_metrics": [
        "Occupancy rates by market",
        "Same-store NOI growth",
        "Debt-to-EBITDA ratio",
        "Interest coverage ratio"
      ],
      "risk_factor_interactions": {
        "recession_plus_oversupply": "Compound impact on occupancy and pricing",
        "interest_rates_plus_refinancing": "Amplified financing costs",
        "correlation_coefficient": 0.65
      }
    },
    "scenario_analysis": {
      "bear_case": {
        "description": "Prolonged market downturn with continued oversupply",
        "assumptions": "Occupancy 85%, pricing down 5%, higher interest rates",
        "revenue_impact": "-15%",
        "valuation_impact": "-25%",
        "probability": 0.20
      },
      "base_case": {
        "description": "Gradual market recovery with stable operations",
        "assumptions": "Occupancy 90%, stable pricing, current interest rates",
        "revenue_impact": "0%",
        "valuation_impact": "0%",
        "probability": 0.60
      },
      "bull_case": {
        "description": "Strong market recovery with synergy realization",
        "assumptions": "Occupancy 93%, pricing up 3%, synergy benefits",
        "revenue_impact": "+12%",
        "valuation_impact": "+20%",
        "probability": 0.20
      },
      "scenario_probabilities": {
        "bear_case": 0.20,
        "base_case": 0.60,
        "bull_case": 0.20
      },
      "confidence": 0.75
    }
  },
  "valuation_model_inputs": {
    "financial_projections": {
      "revenue_forecasts": {
        "2025_revenue": 3260000000,
        "2026_revenue": 3390000000,
        "2027_revenue": 3520000000,
        "growth_assumptions": "Gradual market recovery and synergy realization",
        "key_drivers": "Occupancy improvement and pricing stabilization"
      },
      "margin_projections": {
        "operating_margin_2025": 0.425,
        "operating_margin_2026": 0.435,
        "operating_margin_2027": 0.445,
        "improvement_drivers": "Operational leverage and cost synergies"
      },
      "cash_flow_estimates": {
        "2025_fcf": 1900000000,
        "2026_fcf": 2050000000,
        "2027_fcf": 2200000000,
        "fcf_margin_trajectory": "Improving with operational leverage"
      },
      "confidence": 0.75
    },
    "valuation_parameters": {
      "discount_rates": {
        "wacc": 0.065,
        "cost_of_equity": 0.075,
        "cost_of_debt": 0.045,
        "tax_rate": 0.21
      },
      "terminal_values": {
        "terminal_growth_rate": 0.025,
        "terminal_multiple": 18.0,
        "terminal_fcf_margin": 0.60
      },
      "multiple_ranges": {
        "pe_range": "28-38x",
        "ev_ebitda_range": "16-22x",
        "price_to_ffo_range": "16-22x"
      },
      "confidence": 0.78
    }
  },
  "analytical_insights": {
    "key_findings": [
      "EXR is the largest self-storage operator with strong competitive moats from scale",
      "Financial health is solid with strong cash generation despite market headwinds",
      "Current valuation reflects premium positioning but may be stretched near-term",
      "Life Storage integration provides significant synergy opportunities",
      "Market recovery catalyst could drive substantial upside in 2025-2026"
    ],
    "investment_implications": [
      "Defensive REIT with strong market position and dividend yield",
      "Cyclical exposure to self-storage market creates timing considerations",
      "Premium valuation requires market recovery for attractive returns",
      "Strong balance sheet provides downside protection",
      "Acquisition integration execution key to achieving synergy targets"
    ],
    "analysis_limitations": [
      "Limited visibility into specific market recovery timing",
      "Synergy realization dependent on integration execution",
      "Occupancy data estimates based on industry averages",
      "Competitive dynamics evolving with market consolidation"
    ],
    "follow_up_research": [
      "Detailed occupancy and pricing trends by geographic market",
      "Progress on Life Storage integration and synergy realization",
      "Competitive positioning analysis in top metropolitan markets",
      "Technology platform development and monetization potential"
    ]
  },
  "quality_metrics": {
    "analysis_confidence": 0.82,
    "data_quality_impact": 0.91,
    "methodology_rigor": 0.85,
    "evidence_strength": 0.80
  }
}
